street/__init__.py
street/__version__.py
street/cli.py
street/config.py
street/errors.py
street/exceptions.py
street/scrape.py
street-0.1.2.dist-info/LICENSE
street-0.1.2.dist-info/METADATA
street-0.1.2.dist-info/WHEEL
street-0.1.2.dist-info/entry_points.txt
street-0.1.2.dist-info/top_level.txt
street-0.1.2.dist-info/RECORD
