Metadata-Version: 2.1
Name: street
Version: 0.1.2
Summary: Scrape earnings history from StreetInsider.com
Home-page: https://github.com/kndo/street
Author: Khanh Do
Author-email: dokhanh@gmail.com
License: MIT License
Platform: UNKNOWN
Classifier: Programming Language :: Python
Classifier: Programming Language :: Python :: 3
Requires-Python: >=2.7, !=3.0.*, !=3.1.*, !=3.2.*, !=3.3.*
Requires-Dist: beautifulsoup4
Requires-Dist: click
Requires-Dist: lxml
Requires-Dist: pandas
Requires-Dist: requests
